axltempl/__init__.py
axltempl/click_types.py
axltempl/click_types_test.py
axltempl/composer.py
axltempl/drupal.py
axltempl/gitlab.py
axltempl/lando.py
axltempl/util.py
axltempl/files/drupal/.env.example
axltempl/files/drupal/.gitignore.template
axltempl/files/drupal/composer.json
axltempl/files/drupal/drush.yml
axltempl/files/drupal/load.environment.php
axltempl/files/drupal/renovate.json
axltempl/files/drupal/self.site.yml
axltempl/files/drupal/settings.env.php
axltempl/files/gitlab/ci.sh
axltempl/files/gitlab/gitlab-ci.yml
axltempl/files/gitlab/settings.local.php
axltempl/files/lando/lando.memcache.php
axltempl/files/lando/lando.redis.php
axltempl/files/lando/lando.yml
axltempl/files/lando/php.ini
axltempl/files/lando/settings.lando.php
axl_template-0.6.3.dist-info/LICENSE
axl_template-0.6.3.dist-info/METADATA
axl_template-0.6.3.dist-info/WHEEL
axl_template-0.6.3.dist-info/entry_points.txt
axl_template-0.6.3.dist-info/top_level.txt
axl_template-0.6.3.dist-info/RECORD
