Metadata-Version: 2.1
Name: axl-template
Version: 0.6.3
Summary: Scaffold a Drupal site template
Home-page: https://github.com/axelerant/axl-template
Author: hussainweb
Author-email: hussainweb@gmail.com
License: MIT
Keywords: drupal
Classifier: Development Status :: 4 - Beta
Classifier: Intended Audience :: Developers
Classifier: Topic :: Software Development :: Build Tools
Classifier: Programming Language :: Python :: 3
Requires-Python: >=3.7
License-File: LICENSE
Requires-Dist: Click
